primosconerre/__init__.py
primosconerre-0.1.dist-info/LICENSE
primosconerre-0.1.dist-info/METADATA
primosconerre-0.1.dist-info/WHEEL
primosconerre-0.1.dist-info/top_level.txt
primosconerre-0.1.dist-info/RECORD
