Metadata-Version: 2.1
Name: primosconerre
Version: 0.1
Summary: A tool for calculate prime numbers.
Home-page: UNKNOWN
Author: Pablo Cóceres
Author-email: pablosocialmedia@gmail.com
License: GNU GPLv3
Keywords: primosconerre prime numbers
Platform: UNKNOWN
Classifier: Development Status :: 4 - Beta
Classifier: Intended Audience :: Developers
Classifier: Topic :: Utilities
Classifier: License :: OSI Approved :: GNU General Public License v3 (GPLv3)
Classifier: Programming Language :: Python :: 3
Classifier: Operating System :: OS Independent
